[
  {
    "type": "replace",
    "path": "/stemcells/alias=xenial/version",
    "value": "621.92"
  },
  {
    "type": "replace",
    "path": "/releases/name=concourse",
    "value": {
      "name": "concourse",
      "version": "6.7.1",
      "url": "https://storage.googleapis.com/control-tower-compiled-releases/concourse-6.7.1-ubuntu-xenial-621.92-20201117-103918-919967642.tgz",
      "stemcell": {
        "os": "ubuntu-xenial",
        "version": "621.92"
      }
    }
  },
  {
    "type": "replace",
    "path": "/releases/name=bpm",
    "value": {
      "name": "bpm",
      "version": "1.1.9",
      "url": "https://storage.googleapis.com/control-tower-compiled-releases/bpm-1.1.9-ubuntu-xenial-621.92-20201117-104243-308901493.tgz",
      "stemcell": {
        "os": "ubuntu-xenial",
        "version": "621.92"
      }
    }
  },
  {
    "type": "replace",
    "path": "/releases/name=grafana",
    "value": {
      "name": "grafana",
      "version": "13.3.0",
      "url": "https://storage.googleapis.com/control-tower-compiled-releases/grafana-13.3.0-ubuntu-xenial-621.92-20201117-104257-210367445.tgz",
      "stemcell": {
        "os": "ubuntu-xenial",
        "version": "621.92"
      }
    }
  },
  {
    "type": "replace",
    "path": "/releases/name=influxdb",
    "value": {
      "name": "influxdb",
      "version": "8.0.4",
      "url": "https://storage.googleapis.com/control-tower-compiled-releases/influxdb-8.0.4-ubuntu-xenial-621.92-20201117-104329-431481111.tgz",
      "stemcell": {
        "os": "ubuntu-xenial",
        "version": "621.92"
      }
    }
  },
  {
    "type": "replace",
    "path": "/releases/name=credhub",
    "value": {
      "name": "credhub",
      "version": "2.9.0",
      "url": "https://storage.googleapis.com/control-tower-compiled-releases/credhub-2.9.0-ubuntu-xenial-621.92-20201117-104352-561143539.tgz",
      "stemcell": {
        "os": "ubuntu-xenial",
        "version": "621.92"
      }
    }
  },
  {
    "type": "replace",
    "path": "/releases/name=uaa",
    "value": {
      "name": "uaa",
      "version": "74.28.0",
      "url": "https://storage.googleapis.com/control-tower-compiled-releases/uaa-74.28.0-ubuntu-xenial-621.92-20201117-104506-045522587.tgz",
      "stemcell": {
        "os": "ubuntu-xenial",
        "version": "621.92"
      }
    }
  },
  {
    "type": "replace",
    "path": "/releases/name=bosh-dns",
    "value": {
      "name": "bosh-dns",
      "version": "1.27.0",
      "url": "https://storage.googleapis.com/control-tower-compiled-releases/bosh-dns-1.27.0-ubuntu-xenial-621.92-20201117-104741-004142675.tgz",
      "stemcell": {
        "os": "ubuntu-xenial",
        "version": "621.92"
      }
    }
  },
  {
    "type": "replace",
    "path": "/releases/name=telegraf",
    "value": {
      "name": "telegraf",
      "version": "4",
      "url": "https://storage.googleapis.com/control-tower-compiled-releases/telegraf-4-ubuntu-xenial-621.92-20201117-104751-05138782.tgz",
      "stemcell": {
        "os": "ubuntu-xenial",
        "version": "621.92"
      }
    }
  },
  {
    "type": "replace",
    "path": "/releases/name=telegraf-agent",
    "value": {
      "name": "telegraf-agent",
      "version": "1",
      "url": "https://storage.googleapis.com/control-tower-compiled-releases/telegraf-agent-1-ubuntu-xenial-621.92-20201117-104756-019362839.tgz",
      "stemcell": {
        "os": "ubuntu-xenial",
        "version": "621.92"
      }
    }
  }
]